README.md
setup.py
Giveme5W_enhancer/__init__.py
Giveme5W_enhancer/enhancer/__init__.py
Giveme5W_enhancer/enhancer/abs_enhancer.py
Giveme5W_enhancer/enhancer/aida.py
Giveme5W_enhancer/enhancer/heideltime.py
giveme5w1h_Enhancer.egg-info/PKG-INFO
giveme5w1h_Enhancer.egg-info/SOURCES.txt
giveme5w1h_Enhancer.egg-info/dependency_links.txt
giveme5w1h_Enhancer.egg-info/not-zip-safe
giveme5w1h_Enhancer.egg-info/requires.txt
giveme5w1h_Enhancer.egg-info/top_level.txt