Metadata-Version: 1.1
Name: giveme5w1h-Enhancer
Version: 1.0.0
Summary: Extraction of the journalistic five W and one H questions (5W1H) from news articles.
Home-page: https://github.com/fhamborg/Giveme5W_NewsCluster_enhancer
Author: Felix Hamborg
Author-email: felix.hamborg@uni-konstanz.de
License: Apache License 2.0
Download-URL: https://github.com/fhamborg/Giveme5W_NewsCluster_enhancer
Keywords: question answering news event detection event extraction 5w fivew 5w1h fivewoneh question-answering qa reporters questions
Platform: UNKNOWN
Classifier: Development Status :: 4 - Beta
Classifier: Environment :: Console
Classifier: Intended Audience :: Developers
Classifier: Intended Audience :: Science/Research
Classifier: License :: OSI Approved :: Apache Software License
Classifier: Operating System :: MacOS
Classifier: Operating System :: Microsoft
Classifier: Operating System :: POSIX :: Linux
Classifier: Programming Language :: Python :: 3.6
Classifier: Topic :: Internet
Classifier: Topic :: Scientific/Engineering :: Information Analysis
